{"type": "Feature", "id": 22656436, "properties": {"woe:id": 22656436, "woe:parent_id": 548739, "woe:name": "Fliegerhorst Aigen im Ennstal Airport", "woe:placetype": 14, "woe:placetype_name": "Airport", "woe:lang": "ENG", "iso:country": "AT", "meta:provider": ["geoplanet:7.3.1", "geoplanet:7.3.2", "geoplanet:7.4.0", "geoplanet:7.4.1", "geoplanet:7.5.1", "geoplanet:7.5.2", "geoplanet:7.6.0", "geoplanet:7.8.1", "geoplanet:7.9.0", "geoplanet:7.10.0", "geoplanet:8.0.0", "woeplanet:8.0.0"], "meta:indexed": "2020-08-20T20:54:30.710768", "meta:updated": "2020-08-22T02:30:35.111370", "woe:hierarchy": {"continent": 24865675, "country": 23424750, "town": 0, "planet": 1, "county": 12591723, "suburb": 0, "state": 2344713, "region": 0, "localadmin": 12674811}, "woe:timezone_id": 28350921, "woe:hash": "u26n3tduv9x4", "woe:centroid": [14.13244, 47.535919], "geom:latitude": 47.535919, "geom:longitude": 14.13244, "geom:hash": "u26n3tduv9x4", "woe:latitude": 47.535919, "geom:centroid": [14.13244, 47.535919], "woe:longitude": 14.13244, "woe:repo": "woeplanet-airport-at"}, "geometry": {"coordinates": [14.13244, 47.535919], "type": "Point"}}