{"type": "Feature", "id": 22014356, "geometry": {"type": "Point", "coordinates": [15.44653, 46.99651]}, "properties": {"woe:id": 22014356, "woe:parent_id": 548356, "woe:name": "Flughafen Graz", "woe:placetype": 14, "woe:placetype_name": "Airport", "woe:lang": "GER", "iso:country": "AT", "meta:provider": ["geoplanet:7.3.1", "geoplanet:7.3.2", "geoplanet:7.4.0", "geoplanet:7.4.1", "geoplanet:7.5.1", "geoplanet:7.5.2", "geoplanet:7.6.0", "geoplanet:7.8.1", "geoplanet:7.9.0", "geoplanet:7.10.0", "geoplanet:8.0.0", "woeplanet:8.0.0"], "meta:indexed": "2020-08-20T20:54:30.709888", "woe:alias_FIN_V": ["Grazin Lentokentt\u00e4", "Grazin Lentokentta"], "woe:alias_ENG_V": ["GRZ Airport", "GRZ"], "woe:alias_ITA_V": ["Aeroporto Di Graz"], "woe:alias_ENG_P": ["Graz Airport"], "woe:alias_DAN_V": ["Graz Lufthavn"], "woe:alias_DUT_V": ["Luchthaven Graz"], "woe:alias_POR_V": ["Aeroporto de Graz"], "woe:alias_SWE_V": ["Graz Flygplats"], "meta:updated": "2020-10-14T11:54:48.597597", "woe:alias_GER_V": ["GRZ Flughafen"], "woe:alias_FRE_V": ["Aeroport de Graz", "A\u00e9roport de Graz"], "woe:alias_SPA_V": ["Aeropuerto de Gratz"], "woe:hierarchy": {"continent": 24865675, "country": 23424750, "town": 0, "planet": 1, "county": 12591730, "suburb": 0, "state": 2344713, "region": 0, "localadmin": 12674799}, "woe:timezone_id": 28350921, "woe:hash": "u26gr7ryd0rw", "woe:centroid": [15.44653, 46.99651], "geom:latitude": 46.99651, "geom:longitude": 15.44653, "geom:hash": "u26gr7ryd0rw", "woe:latitude": 46.99651, "geom:centroid": [15.44653, 46.99651], "woe:longitude": 15.44653, "woe:repo": "woeplanet-airport-at", "geom:area": 0.0, "woe:scale": 19}}