{"type": "Feature", "id": 56051690, "properties": {"woe:id": 56051690, "woe:parent_id": 544952, "woe:name": "Flugplatz Eferding", "woe:placetype": 14, "woe:placetype_name": "Airport", "woe:lang": "GER", "iso:country": "AT", "meta:provider": ["geoplanet:7.3.1", "geoplanet:7.3.2", "geoplanet:7.4.0", "geoplanet:7.4.1", "geoplanet:7.5.1", "geoplanet:7.5.2", "geoplanet:7.6.0", "geoplanet:7.8.1", "geoplanet:7.9.0", "geoplanet:7.10.0", "geoplanet:8.0.0", "woeplanet:8.0.0"], "meta:indexed": "2020-08-20T20:54:30.731548", "meta:updated": "2020-08-22T02:30:35.121665", "woe:hierarchy": {"continent": 24865675, "country": 23424750, "town": 0, "planet": 1, "county": 12591719, "suburb": 0, "state": 2344711, "region": 0, "localadmin": 12674413}, "woe:timezone_id": 28350921, "woe:hash": "u29gn0rckt7r", "woe:centroid": [13.98545, 48.341461], "geom:latitude": 48.341461, "geom:longitude": 13.98545, "geom:hash": "u29gn0rckt7r", "woe:latitude": 48.341461, "geom:centroid": [13.98545, 48.341461], "woe:longitude": 13.98545, "woe:repo": "woeplanet-airport-at"}, "geometry": {"coordinates": [13.98545, 48.341461], "type": "Point"}}