{"type": "Feature", "id": 56051703, "properties": {"woe:id": 56051703, "woe:parent_id": 549430, "woe:name": "Flugfeld Nieder\u00f6blarn", "woe:placetype": 14, "woe:placetype_name": "Airport", "woe:lang": "GER", "iso:country": "AT", "meta:provider": ["geoplanet:7.3.1", "geoplanet:7.3.2", "geoplanet:7.4.0", "geoplanet:7.4.1", "geoplanet:7.5.1", "geoplanet:7.5.2", "geoplanet:7.6.0", "geoplanet:7.8.1", "geoplanet:7.9.0", "geoplanet:7.10.0", "geoplanet:8.0.0", "woeplanet:8.0.0"], "meta:indexed": "2020-08-20T20:54:30.743685", "meta:updated": "2020-08-22T02:30:35.127199", "woe:alias_GER_S": ["Flugfeld Niederoblarn"], "woe:hierarchy": {"continent": 24865675, "country": 23424750, "town": 0, "planet": 1, "county": 12591723, "suburb": 0, "state": 2344713, "region": 0, "localadmin": 12675103}, "woe:timezone_id": 28350921, "woe:hash": "u23yngepmbe9", "woe:centroid": [14.01194, 47.481411], "geom:latitude": 47.481411, "geom:longitude": 14.01194, "geom:hash": "u23yngepmbe9", "woe:latitude": 47.481411, "geom:centroid": [14.01194, 47.481411], "woe:longitude": 14.01194, "woe:repo": "woeplanet-airport-at"}, "geometry": {"coordinates": [14.01194, 47.481411], "type": "Point"}}