{"type": "Feature", "id": 22022012, "geometry": {"type": "Point", "coordinates": [16.55854, 48.124229]}, "properties": {"woe:id": 22022012, "woe:parent_id": 542412, "woe:name": "Flughafen Wien-Schwechat", "woe:placetype": 14, "woe:placetype_name": "Airport", "woe:lang": "GER", "iso:country": "AT", "meta:provider": ["geoplanet:7.3.1", "geoplanet:7.3.2", "geoplanet:7.4.0", "geoplanet:7.4.1", "geoplanet:7.5.1", "geoplanet:7.5.2", "geoplanet:7.6.0", "geoplanet:7.8.1", "geoplanet:7.9.0", "geoplanet:7.10.0", "geoplanet:8.0.0", "woeplanet:8.0.0"], "meta:indexed": "2020-08-20T20:54:30.717769", "woe:alias_FIN_V": ["Wienin Lentokentta", "Wienin Lentokentt\u00e4"], "woe:alias_ENG_V": ["VIE", "Schwechat Airport", "VIE Airport", "Vienna Airport", "Vienna International Airport"], "woe:alias_ITA_V": ["Aeroporto Di Vienne"], "woe:alias_ENG_P": ["Vienna Schwechat International Airport"], "woe:alias_DAN_V": ["Wien Lufthavn"], "woe:alias_DUT_V": ["Luchthaven Wenen"], "woe:alias_POR_V": ["Aeroporto de Viena"], "woe:alias_SWE_V": ["Wien Flygplats"], "meta:updated": "2020-10-14T11:54:48.598291", "woe:alias_GER_V": ["Flughafen Wien", "Wien-Schwechat", "VIE Flughafen"], "woe:alias_FRE_V": ["A\u00e9roport de Vienne", "Aeroport de Vienne"], "woe:hierarchy": {"continent": 24865675, "country": 23424750, "town": 0, "planet": 1, "county": 12591694, "suburb": 0, "state": 2344710, "region": 0, "localadmin": 12673957}, "woe:timezone_id": 28350921, "woe:hash": "u2ecbb9xcyqr", "woe:centroid": [16.55854, 48.124229], "geom:latitude": 48.124229, "geom:longitude": 16.55854, "geom:hash": "u2ecbb9xcyqr", "woe:latitude": 48.124229, "geom:centroid": [16.55854, 48.124229], "woe:longitude": 16.55854, "woe:repo": "woeplanet-airport-at", "geom:area": 0.0, "woe:scale": 19}}