{"type": "Feature", "id": 56051694, "properties": {"woe:id": 56051694, "woe:parent_id": 543817, "woe:name": "Flugplatz Seitenstetten", "woe:placetype": 14, "woe:placetype_name": "Airport", "woe:lang": "GER", "iso:country": "AT", "meta:provider": ["geoplanet:7.3.1", "geoplanet:7.3.2", "geoplanet:7.4.0", "geoplanet:7.4.1", "geoplanet:7.5.1", "geoplanet:7.5.2", "geoplanet:7.6.0", "geoplanet:7.8.1", "geoplanet:7.9.0", "geoplanet:7.10.0", "geoplanet:8.0.0", "woeplanet:8.0.0"], "meta:indexed": "2020-08-20T20:54:30.735610", "meta:updated": "2020-08-22T02:30:35.123361", "woe:hierarchy": {"continent": 24865675, "country": 23424750, "town": 0, "planet": 1, "county": 12591680, "suburb": 0, "state": 2344710, "region": 0, "localadmin": 12673864}, "woe:timezone_id": 28350921, "woe:hash": "u2d3mee344yv", "woe:centroid": [14.66032, 48.05164], "geom:latitude": 48.05164, "geom:longitude": 14.66032, "geom:hash": "u2d3mee344yv", "woe:latitude": 48.05164, "geom:centroid": [14.66032, 48.05164], "woe:longitude": 14.66032, "woe:repo": "woeplanet-airport-at"}, "geometry": {"coordinates": [14.66032, 48.05164], "type": "Point"}}